[
    {
        "fecha_hora_utc3": "2025-02-23 14:14:09",
        "compra": "1210,00",
        "venta": "1230,00"
    },
    {
        "fecha_hora_utc3": "2025-02-23 15:27:12",
        "compra": "1210,00",
        "venta": "1230,00"
    },
    {
        "fecha_hora_utc3": "2025-02-23 16:14:35",
        "compra": "1210,00",
        "venta": "1230,00"
    },
    {
        "fecha_hora_utc3": "2025-02-23 17:07:24",
        "compra": "1210,00",
        "venta": "1230,00"
    },
    {
        "fecha_hora_utc3": "2025-02-23 18:18:38",
        "compra": "1210,00",
        "venta": "1230,00"
    },
    {
        "fecha_hora_utc3": "2025-02-24 09:27:08",
        "compra": "1210,00",
        "venta": "1230,00"
    },
    {
        "fecha_hora_utc3": "2025-02-24 10:22:25",
        "compra": "1210,00",
        "venta": "1230,00"
    },
    {
        "fecha_hora_utc3": "2025-02-24 11:22:21",
        "compra": "1210,00",
        "venta": "1230,00"
    },
    {
        "fecha_hora_utc3": "2025-02-24 12:21:51",
        "compra": "1210,00",
        "venta": "1230,00"
    }
]