[
    {
        "fecha_hora_utc3": "2025-11-09 12:20:52",
        "compra": "1395,00",
        "venta": "1415,00"
    },
    {
        "fecha_hora_utc3": "2025-11-09 13:13:00",
        "compra": "1395,00",
        "venta": "1415,00"
    },
    {
        "fecha_hora_utc3": "2025-11-09 14:17:28",
        "compra": "1395,00",
        "venta": "1415,00"
    },
    {
        "fecha_hora_utc3": "2025-11-09 15:33:14",
        "compra": "1395,00",
        "venta": "1415,00"
    },
    {
        "fecha_hora_utc3": "2025-11-09 16:17:56",
        "compra": "1395,00",
        "venta": "1415,00"
    },
    {
        "fecha_hora_utc3": "2025-11-09 17:10:46",
        "compra": "1395,00",
        "venta": "1415,00"
    },
    {
        "fecha_hora_utc3": "2025-11-09 18:17:26",
        "compra": "1395,00",
        "venta": "1415,00"
    }
]