[
    {
        "fecha_hora_utc3": "2026-03-17 18:39:20",
        "compra": "1372,11",
        "venta": "1422,26"
    },
    {
        "fecha_hora_utc3": "2026-03-18 10:00:18",
        "compra": "1372,11",
        "venta": "1422,26"
    },
    {
        "fecha_hora_utc3": "2026-03-18 11:17:34",
        "compra": "1372,11",
        "venta": "1422,26"
    },
    {
        "fecha_hora_utc3": "2026-03-18 12:12:03",
        "compra": "1372,11",
        "venta": "1422,26"
    },
    {
        "fecha_hora_utc3": "2026-03-18 13:09:11",
        "compra": "1372,11",
        "venta": "1422,26"
    },
    {
        "fecha_hora_utc3": "2026-03-18 13:50:23",
        "compra": "1372,11",
        "venta": "1422,26"
    },
    {
        "fecha_hora_utc3": "2026-03-18 14:59:55",
        "compra": "1372,11",
        "venta": "1422,26"
    },
    {
        "fecha_hora_utc3": "2026-03-18 16:11:31",
        "compra": "1367,61",
        "venta": "1418,18"
    },
    {
        "fecha_hora_utc3": "2026-03-18 16:50:10",
        "compra": "1367,61",
        "venta": "1418,18"
    }
]