[
    {
        "fecha_hora_utc3": "2026-02-11 18:36:03",
        "compra": "1376,80",
        "venta": "1427,34"
    },
    {
        "fecha_hora_utc3": "2026-02-12 09:57:44",
        "compra": "1376,80",
        "venta": "1427,34"
    },
    {
        "fecha_hora_utc3": "2026-02-12 11:05:50",
        "compra": "1376,80",
        "venta": "1427,34"
    },
    {
        "fecha_hora_utc3": "2026-02-12 11:55:44",
        "compra": "1368,21",
        "venta": "1418,59"
    },
    {
        "fecha_hora_utc3": "2026-02-12 12:56:18",
        "compra": "1368,21",
        "venta": "1418,59"
    },
    {
        "fecha_hora_utc3": "2026-02-12 13:47:36",
        "compra": "1368,21",
        "venta": "1418,59"
    },
    {
        "fecha_hora_utc3": "2026-02-12 14:56:55",
        "compra": "1367,11",
        "venta": "1417,46"
    },
    {
        "fecha_hora_utc3": "2026-02-12 16:12:39",
        "compra": "1367,11",
        "venta": "1417,46"
    },
    {
        "fecha_hora_utc3": "2026-02-12 16:49:56",
        "compra": "1370,09",
        "venta": "1420,27"
    },
    {
        "fecha_hora_utc3": "2026-02-12 17:22:32",
        "compra": "1370,09",
        "venta": "1420,27"
    }
]