[
    {
        "fecha_hora_utc3": "2025-07-12 11:23:15",
        "compra": "1280,00",
        "venta": "1300,00"
    },
    {
        "fecha_hora_utc3": "2025-07-12 12:21:44",
        "compra": "1280,00",
        "venta": "1300,00"
    },
    {
        "fecha_hora_utc3": "2025-07-12 13:13:24",
        "compra": "1280,00",
        "venta": "1300,00"
    },
    {
        "fecha_hora_utc3": "2025-07-12 14:16:36",
        "compra": "1280,00",
        "venta": "1300,00"
    },
    {
        "fecha_hora_utc3": "2025-07-12 15:33:39",
        "compra": "1280,00",
        "venta": "1300,00"
    },
    {
        "fecha_hora_utc3": "2025-07-12 16:17:51",
        "compra": "1280,00",
        "venta": "1300,00"
    }
]